[
    {
        "id": "63346a797c8b6a16b0a9fd21",
        "picture": "https://i.ibb.co/xFQMdrV/1.png",
        "age": 28,
        "name": "Slater",
        "registered": "{Amet minim mollit non deserunt ullamco est sit aliqua dolor do amet sint}",
        "time": "50:30"
    },
    {
        "id": "63346a797c8b6a16b0a9fd22",
        "picture": "https://i.ibb.co/gDjgsXG/2.png",
        "age": 26,
        "name": "Slater",
        "registered": "{Amet minim mollit non deserunt ullamco est sit aliqua dolor do amet sint}",
        "time": "30:30"
    },
    {
        "id": "63346a797c8b6a16b0a9fd23",
        "picture": "https://i.ibb.co/tJpXctq/3.png",
        "age": 29,
        "name": "Slater",
        "registered": "{Amet minim mollit non deserunt ullamco est sit aliqua dolor do amet sint}",
        "time": "55:30"
    },
    {
        "id": "63346a797c8b6a16b0a9fd24",
        "picture": "https://i.ibb.co/FqpJrxc/4.png",
        "age": 22,
        "name": "Slater",
        "registered": "{Amet minim mollit non deserunt ullamco est sit aliqua dolor do amet sint}",
        "time": "46:33"
    },
    {
        "id": "63346a797c8b6a16b0a9fd25",
        "picture": "https://i.ibb.co/SBbmbRt/5.png",
        "age": 25,
        "name": "Slater",
        "registered": "{Amet minim mollit non deserunt ullamco est sit aliqua dolor do amet sint}",
        "time": "45:33"
    },
    {
        "id": "63346a797c8b6a16b0a9fd26",
        "picture": "https://i.ibb.co/QcykRCL/6.png",
        "age": 28,
        "name": "Slater",
        "registered": "{Amet minim mollit non deserunt ullamco est sit aliqua dolor do amet sint}",
        "time": "53:38"
    },
    {
        "id": "63346a797c8b6a16b0a9fd27",
        "picture": "https://i.ibb.co/0Fx7zxb/7.png",
        "age": 32,
        "name": "Slater",
        "registered": "{Amet minim mollit non deserunt ullamco est sit aliqua dolor do amet sint}",
        "time": "57:30"
    },
    {
        "id": "63346a797c8b6a16b0a9fd28",
        "picture": "https://i.ibb.co/3krkmtj/8.png",
        "age": 32,
        "name": "Slater",
        "registered": "{Amet minim mollit non deserunt ullamco est sit aliqua dolor do amet sint}",
        "time": "75:33"
    },
    {
        "id": "63346a797c8b6a16b0a9fd29",
        "picture": "https://i.ibb.co/YWY8BHg/9.png",
        "age": 22,
        "name": "Slater",
        "registered": "{Amet minim mollit non deserunt ullamco est sit aliqua dolor do amet sint}",
        "time": "53:32"
    },
    {
        "id": "63346a797c8b6a16b0a9fd30",
        "picture": "https://i.ibb.co/0cY8zJ1/10.png",
        "age": 20,
        "name": "Slater",
        "registered": "{Amet minim mollit non deserunt ullamco est sit aliqua dolor do amet sint}",
        "time": "62:43"
    },
    {
        "id": "63346a797c8b6a16b0a9fd31",
        "picture": "https://i.ibb.co/fG9Vwbn/12.png",
        "age": 24,
        "name": "Slater",
        "registered": "{Amet minim mollit non deserunt ullamco est sit aliqua dolor do amet sint}",
        "time": "54:36"
    }
]